py_search/__init__.py
py_search/base.py
py_search/informed.py
py_search/optimization.py
py_search/uninformed.py
py_search/utils.py
py_search/problems/__init__.py
py_search/problems/assignment_problem.py
py_search/problems/eight_puzzle.py
py_search/problems/graph_partition.py
py_search/problems/nqueens.py
py_search-2.8.0.dist-info/LICENSE.txt
py_search-2.8.0.dist-info/METADATA
py_search-2.8.0.dist-info/WHEEL
py_search-2.8.0.dist-info/pbr.json
py_search-2.8.0.dist-info/top_level.txt
py_search-2.8.0.dist-info/RECORD
